{
  "title": "Vom Rechner zum Bankgespräch",
  "category": "Finanzierung",
  "summary": "Eine nachvollziehbare Kalkulation verbessert die Vorbereitung.",
  "body": "Banken benötigen zusätzlich Einkommens-, Vermögens-, Objekt- und Mietunterlagen sowie eigene Bewertungsannahmen.",
  "id": "vom-rechner-zum-bankgesprach",
  "slug": "vom-rechner-zum-bankgesprach",
  "url": "/wissen/vom-rechner-zum-bankgesprach/",
  "keywords": [
    "bankgespräch",
    "eine",
    "kalkulation",
    "nachvollziehbare",
    "rechner",
    "verbessert",
    "vorbereitung"
  ],
  "synonyms": [],
  "updated": "2026-07-16",
  "author": "Fischer & Geserich Real Estate GmbH",
  "related": []
}